[[],{"name":"gksdg","tel":"54645","email":"dd@f.r","date":"22222222"},[],{"name":"huhu","tel":"huhu","email":"huhu@huhu.tu"},[],{"name":"tututut","tel":"tututut","email":"tututut@tututut.ry","date":"2020-11-15 06:06:31"},[],{"name":"g","tel":"g","email":"g@n.ru","date":"2020-11-16 02:04:58"},[],{"name":"hj","tel":"j","email":"h@j.u","date":"2020-11-16 02:05:24"},[],{"name":"rer","tel":"reter","email":"sas@t.t","date":"2020-11-16 02:47:06"},[],{"name":"tgfj","tel":"tgfj","email":"tgfj@tgfj.ry","date":"2020-11-16 02:54:28"}]